SparkBianchengZhinan/README.md
SparkBianchengZhinan/__init__.py
SparkBianchengZhinan/__main__.py
SparkBianchengZhinan/file.epub
SparkBianchengZhinan/index.html
SparkBianchengZhinan/css/__init__.py
SparkBianchengZhinan/css/annotations.css
SparkBianchengZhinan/css/main.css
SparkBianchengZhinan/css/normalize.css
SparkBianchengZhinan/css/popup.css
SparkBianchengZhinan/font/__init__.py
SparkBianchengZhinan/font/fontello.eot
SparkBianchengZhinan/font/fontello.svg
SparkBianchengZhinan/font/fontello.ttf
SparkBianchengZhinan/font/fontello.woff
SparkBianchengZhinan/img/__init__.py
SparkBianchengZhinan/img/annotator-glyph-sprite.png
SparkBianchengZhinan/img/annotator-icon-sprite.png
SparkBianchengZhinan/img/apple-touch-icon.png
SparkBianchengZhinan/img/cancelfullscreen.png
SparkBianchengZhinan/img/close.png
SparkBianchengZhinan/img/fullscreen.png
SparkBianchengZhinan/img/loader.gif
SparkBianchengZhinan/img/menu-icon.png
SparkBianchengZhinan/img/save.png
SparkBianchengZhinan/img/saved.png
SparkBianchengZhinan/img/settings-s.png
SparkBianchengZhinan/img/settings.png
SparkBianchengZhinan/img/star.png
SparkBianchengZhinan/js/__init__.py
SparkBianchengZhinan/js/epub.js
SparkBianchengZhinan/js/epub.min.js
SparkBianchengZhinan/js/epub.min.map
SparkBianchengZhinan/js/hooks.min.js
SparkBianchengZhinan/js/hooks.min.map
SparkBianchengZhinan/js/reader.js
SparkBianchengZhinan/js/reader.js.map
SparkBianchengZhinan/js/reader.min.js
SparkBianchengZhinan/js/reader.min.map
SparkBianchengZhinan/js/hooks/__init__.py
SparkBianchengZhinan/js/hooks/extensions/__init__.py
SparkBianchengZhinan/js/hooks/extensions/highlight.js
SparkBianchengZhinan/js/libs/__init__.py
SparkBianchengZhinan/js/libs/jquery.min.js
SparkBianchengZhinan/js/libs/localforage.min.js
SparkBianchengZhinan/js/libs/screenfull.js
SparkBianchengZhinan/js/libs/screenfull.min.js
SparkBianchengZhinan/js/libs/zip.min.js
SparkBianchengZhinan/js/plugins/__init__.py
SparkBianchengZhinan/js/plugins/hypothesis.js
spark_biancheng_zhinan-2024.3.2.0.dist-info/METADATA
spark_biancheng_zhinan-2024.3.2.0.dist-info/WHEEL
spark_biancheng_zhinan-2024.3.2.0.dist-info/entry_points.txt
spark_biancheng_zhinan-2024.3.2.0.dist-info/top_level.txt
spark_biancheng_zhinan-2024.3.2.0.dist-info/RECORD
